readability/__init__.py
readability/browser.py
readability/cleaners.py
readability/debug.py
readability/encoding.py
readability/htmls.py
readability/readability.py
readability_lxml-0.8.4.1.dist-info/LICENSE
readability_lxml-0.8.4.1.dist-info/METADATA
readability_lxml-0.8.4.1.dist-info/WHEEL
readability_lxml-0.8.4.1.dist-info/top_level.txt
readability_lxml-0.8.4.1.dist-info/RECORD
