Metadata-Version: 2.1
Name: readability-lxml
Version: 0.8.4.1
Summary: fast html to text parser (article readability tool) with python 3 support
Home-page: http://github.com/buriy/python-readability
Author: Yuri Baburov
Author-email: burchik@gmail.com
License: Apache License 2.0
Classifier: Environment :: Web Environment
Classifier: Intended Audience :: Developers
Classifier: Operating System :: OS Independent
Classifier: Topic :: Text Processing :: Indexing
Classifier: Topic :: Utilities
Classifier: Topic :: Internet
Classifier: Topic :: Software Development :: Libraries :: Python Modules
Classifier: Programming Language :: Python
Classifier: Programming Language :: Python :: 3
Classifier: Programming Language :: Python :: 3.8
Classifier: Programming Language :: Python :: 3.9
Classifier: Programming Language :: Python :: 3.10
Classifier: Programming Language :: Python :: 3.11
Classifier: Programming Language :: Python :: 3.12
Classifier: Programming Language :: Python :: 3.13
Classifier: Programming Language :: Python :: Implementation :: PyPy
License-File: LICENSE
Requires-Dist: chardet
Requires-Dist: lxml[html_clean]
Requires-Dist: lxml-html-clean; python_version < "3.11"
Requires-Dist: cssselect
Provides-Extra: speed
Requires-Dist: cchardet; extra == "speed"
